banditml/__init__.py
banditml/data_reader/__init__.py
banditml/data_reader/reader.py
banditml/db/__init__.py
banditml/db/bq.py
banditml/db/v1.py
banditml/db/v2.py
banditml/models/__init__.py
banditml/models/benchmarks.py
banditml/models/embed_dnn.py
banditml/preprocessing/__init__.py
banditml/preprocessing/preprocessor.py
banditml/serving/__init__.py
banditml/serving/predictor.py
banditml/training/__init__.py
banditml/training/trainer.py
banditml/utils/__init__.py
banditml/utils/feature_importance.py
banditml/utils/model_constructors.py
banditml/utils/model_trainers.py
banditml/utils/utils.py
banditml-1.0.2.dist-info/METADATA
banditml-1.0.2.dist-info/WHEEL
banditml-1.0.2.dist-info/top_level.txt
banditml-1.0.2.dist-info/RECORD
