Metadata-Version: 2.1
Name: banditml
Version: 1.0.2
Summary: Lightweight library for training & serving contextual bandit models.
Home-page: https://github.com/banditml/banditml
Author: Edoardo Conti, Lionel Vital, Joseph Gilley
Author-email: team@banditml.com
License: UNKNOWN
Platform: UNKNOWN
Classifier: Programming Language :: Python :: 3
Classifier: License :: OSI Approved :: GNU General Public License (GPL)
Classifier: Operating System :: OS Independent
Requires-Python: >=3.6
Requires-Dist: torch (~=1.7.0)
Requires-Dist: pandas (~=1.1.4)
Requires-Dist: google-cloud-bigquery (~=1.24)
Requires-Dist: scikit-learn (<0.23,>=0.22.2.post1)
Requires-Dist: skorch (~=0.9.0)
